filteralchemy/__init__.py
filteralchemy/filters.py
filteralchemy/filterset.py
filteralchemy/formatters.py
filteralchemy/operators.py
filteralchemy/utils.py
filteralchemy-0.1.0.dist-info/DESCRIPTION.rst
filteralchemy-0.1.0.dist-info/METADATA
filteralchemy-0.1.0.dist-info/RECORD
filteralchemy-0.1.0.dist-info/WHEEL
filteralchemy-0.1.0.dist-info/metadata.json
filteralchemy-0.1.0.dist-info/top_level.txt
