Metadata-Version: 1.1
Name: filteralchemy
Version: 0.1.0
Summary: Declarative query builder for SQLAlchemy
Home-page: https://github.com/jmcarp/filteralchemy
Author: Joshua Carp
Author-email: jm.carp@gmail.com
License: Copyright 2015 Joshua Carp
